<?xml version="1.0" encoding="utf-8" ?>
<!--Debe existir un match entre los valores del enum, con los códigos acá expuestos, aquellos que no se encuentre en el enum, no serán insertados.-->
<ArrayOfTransManualOrAutomaticType>
  <TransManualOrAutomaticType>
    <ManualOrAutomatic>0</ManualOrAutomatic>
    <Description>None</Description>
    <ShortDescription>None</ShortDescription>
    <LanguageID>1</LanguageID>
  </TransManualOrAutomaticType>
  <TransManualOrAutomaticType>
    <ManualOrAutomatic>0</ManualOrAutomatic>
    <Description>Ninguno</Description>
    <ShortDescription>Ninguno</ShortDescription>
    <LanguageID>2</LanguageID>
  </TransManualOrAutomaticType>
  <TransManualOrAutomaticType>
    <ManualOrAutomatic>1</ManualOrAutomatic>
    <Description>Automatic</Description>
    <ShortDescription>Automatic</ShortDescription>
    <LanguageID>1</LanguageID>
  </TransManualOrAutomaticType>
  <TransManualOrAutomaticType>
    <ManualOrAutomatic>1</ManualOrAutomatic>
    <Description>Automático</Description>
    <ShortDescription>Automático</ShortDescription>
    <LanguageID>2</LanguageID>
  </TransManualOrAutomaticType>
  <TransManualOrAutomaticType>
    <ManualOrAutomatic>2</ManualOrAutomatic>
    <Description>Manual</Description>
    <ShortDescription>Manual</ShortDescription>
    <LanguageID>1</LanguageID>
  </TransManualOrAutomaticType>
  <TransManualOrAutomaticType>
    <ManualOrAutomatic>2</ManualOrAutomatic>
    <Description>Manual</Description>
    <ShortDescription>Manual</ShortDescription>
    <LanguageID>2</LanguageID>
  </TransManualOrAutomaticType>
</ArrayOfTransManualOrAutomaticType>