<?xml version="1.0" encoding="utf-8"?><metadata xmlns:xsd="http://www.w3.org/2001/XMLSchema" xmlns:xsi="http://www.w3.org/2001/XMLSchema-instance" name="Audio_DLI" Repository="DNE" UserInput="ARCHIVO_SONIDO_DLI.ID_SECUENCIA,Sequence id/Id secuencia,Numeric,Secuencia|ARCHIVO_SONIDO_DLI.ID_CONSECUTIVO,Consequence id/Id consecutivo,Numeric,Consecutivo" version="2.1.0" ModelId="1ce28334-0c72-46be-90f6-1745d6aaeeca" Release="1" NumberOfColumns="3"><titles /><summaries /><root name="ARCHIVO_SONIDO_DLI" Key="0" EntityType="Table" Identify="ARCHIVO_SONIDO_DLI.ID_SECUENCIA,ARCHIVO_SONIDO_DLI.ID_CONSECUTIVO" ParentRelationshipList="RECURSO_DNE_DLI" PageSize="10" Source="DNE" VerifyHaveRecords="true"><captions><caption Language="1" Value="Sound file" /><caption Language="2" Value="Archivo Sonido" /></captions><QueryStatements><RetrieveAll>SELECT ARCHIVO_SONIDO_DLI.ROWID AS RECORDID, ARCHIVO_SONIDO_DLI.ID_SECUENCIA,ARCHIVO_SONIDO_DLI.ID_CONSECUTIVO, ARCHIVO_SONIDO_DLI.ID_SECUENCIA, ARCHIVO_SONIDO_DLI.ID_CONSECUTIVO, RECURSO_DNE_DLI1.DESCRIPCION AS RECURSO_DNE_DLIDESCRIPCION, RECURSO_DNE_DLI1.NOMBRE AS RECURSO_DNE_DLINOMBRE, ARCHIVO_SONIDO_DLI.ARCHIVO_SONIDO, ARCHIVO_SONIDO_DLI.ID_CONSECUTIVO, ARCHIVO_SONIDO_DLI.ID_SECUENCIA FROM ARCHIVO_SONIDO_DLI LEFT JOIN RECURSO_DNE_DLI RECURSO_DNE_DLI1 ON RECURSO_DNE_DLI1.ID_SECUENCIA = ARCHIVO_SONIDO_DLI.ID_SECUENCIA AND RECURSO_DNE_DLI1.ID_CONSECUTIVO = ARCHIVO_SONIDO_DLI.ID_CONSECUTIVO WHERE ARCHIVO_SONIDO_DLI.ID_SECUENCIA = [SECUENCIA] AND ARCHIVO_SONIDO_DLI.ID_CONSECUTIVO = [CONSECUTIVO]  ORDER BY ARCHIVO_SONIDO_DLI.ID_SECUENCIA, ARCHIVO_SONIDO_DLI.ID_CONSECUTIVO</RetrieveAll><AllParameters>[SECUENCIA],[CONSECUTIVO]</AllParameters><RetrieveByKey>SELECT ARCHIVO_SONIDO_DLI.ROWID AS RECORDID, ARCHIVO_SONIDO_DLI.ID_SECUENCIA,ARCHIVO_SONIDO_DLI.ID_CONSECUTIVO, ARCHIVO_SONIDO_DLI.ID_SECUENCIA, ARCHIVO_SONIDO_DLI.ID_CONSECUTIVO, RECURSO_DNE_DLI1.DESCRIPCION AS RECURSO_DNE_DLIDESCRIPCION, RECURSO_DNE_DLI1.NOMBRE AS RECURSO_DNE_DLINOMBRE, ARCHIVO_SONIDO_DLI.ARCHIVO_SONIDO, ARCHIVO_SONIDO_DLI.ID_CONSECUTIVO, ARCHIVO_SONIDO_DLI.ID_SECUENCIA FROM ARCHIVO_SONIDO_DLI LEFT JOIN RECURSO_DNE_DLI RECURSO_DNE_DLI1 ON RECURSO_DNE_DLI1.ID_SECUENCIA = ARCHIVO_SONIDO_DLI.ID_SECUENCIA AND RECURSO_DNE_DLI1.ID_CONSECUTIVO = ARCHIVO_SONIDO_DLI.ID_CONSECUTIVO WHERE ARCHIVO_SONIDO_DLI.ID_SECUENCIA = {ID_SECUENCIA} AND ARCHIVO_SONIDO_DLI.ID_CONSECUTIVO = {ID_CONSECUTIVO}</RetrieveByKey><KeyParameters>{ID_SECUENCIA},{ID_CONSECUTIVO}</KeyParameters><IsExist>SELECT COUNT(*) FROM ARCHIVO_SONIDO_DLI LEFT JOIN RECURSO_DNE_DLI RECURSO_DNE_DLI1 ON RECURSO_DNE_DLI1.ID_SECUENCIA = ARCHIVO_SONIDO_DLI.ID_SECUENCIA AND RECURSO_DNE_DLI1.ID_CONSECUTIVO = ARCHIVO_SONIDO_DLI.ID_CONSECUTIVO WHERE ARCHIVO_SONIDO_DLI.ID_SECUENCIA = [SECUENCIA] AND ARCHIVO_SONIDO_DLI.ID_CONSECUTIVO = [CONSECUTIVO] </IsExist><ParameterToChilds>ID_SECUENCIA,ID_CONSECUTIVO</ParameterToChilds></QueryStatements><Parameters /><pluralcaptions><pluralcaption Language="1" Value="Sound files" /><pluralcaption Language="2" Value="Archivo Sonidos" /></pluralcaptions><columns><columnquery name="RECURSO_DNE_DLI.DESCRIPCION" xmlType="xmlNVarChar" Visible="true" StyleLookup="Code"><captions><caption Language="1" Value="Description" /><caption Language="2" Value="Descripcion" /></captions><ToolTips><ToolTip Language="1" Value="Description of the code." /><ToolTip Language="2" Value="Descripción del código." /></ToolTips><ColumnSource RelationshipColumns="" Description="" StyleValue="Code" Language="" /><AggregateLabels /></columnquery><columnquery name="RECURSO_DNE_DLI.NOMBRE" xmlType="xmlNVarChar" Visible="true" StyleLookup="Code"><captions><caption Language="1" Value="NOMBRE" /><caption Language="2" Value="NOMBRE" /></captions><ToolTips><ToolTip Language="1" Value="Sequence name.&#xA;//&#xA;Nombre de la secuencia." /><ToolTip Language="2" Value="Sequence name.&#xA;//&#xA;Nombre de la secuencia." /></ToolTips><ColumnSource RelationshipColumns="" Description="" StyleValue="Code" Language="" /><AggregateLabels /></columnquery><columnquery name="ARCHIVO_SONIDO_DLI.ARCHIVO_SONIDO" xmlType="xmlBinary" Style="ImageDetail" Visible="true" StyleLookup="Code"><captions><caption Language="1" Value="Sound file" /><caption Language="2" Value="Archivo de sonido" /></captions><ToolTips><ToolTip Language="1" Value="Sound file.&#xA;" /><ToolTip Language="2" Value="Archivo de sonido." /></ToolTips><ColumnSource RelationshipColumns="" Description="" StyleValue="Code" Language="" /><AggregateLabels /></columnquery><columnquery name="ARCHIVO_SONIDO_DLI.ID_CONSECUTIVO" xmlType="xmlNumeric" precision="10" Visible="true" StyleLookup="Code"><captions><caption Language="1" Value="Consequence id" /><caption Language="2" Value="Id consecutivo" /></captions><ToolTips><ToolTip Language="1" Value="Consequence id" /><ToolTip Language="2" Value="Id consecutivo" /></ToolTips><ColumnSource RelationshipColumns="" Description="" StyleValue="Code" Language="" /><AggregateLabels /></columnquery><columnquery name="ARCHIVO_SONIDO_DLI.ID_SECUENCIA" xmlType="xmlNumeric" precision="10" Visible="true" StyleLookup="Code"><captions><caption Language="1" Value="Sequence id" /><caption Language="2" Value="Id secuencia" /></captions><ToolTips><ToolTip Language="1" Value="Identifier of the sequence." /><ToolTip Language="2" Value="Identificador de la secuencia." /></ToolTips><ColumnSource RelationshipColumns="" Description="" StyleValue="Code" Language="" /><AggregateLabels /></columnquery></columns><childs /><titles><title Language="1" /></titles><titlesQuery><titleQuery Language="1" Value="Audio_DLI" /><titleQuery Language="2" Value="Audio_DLI" /></titlesQuery><descriptionsQuery><descriptionQuery Language="1" Value="Audio_DLI" /><descriptionQuery Language="2" Value="Audio_DLI" /></descriptionsQuery><Remarks><Remark Language="1" Value="Sound content table." /><Remark Language="2" Value="Tabla de contenido de sonido." /></Remarks><ContextMenu /><ActionFilters /><StyleList /><Filters><Condition Name="ARCHIVO_SONIDO_DLI.ID_SECUENCIA" Expression="[Secuencia]" Operator="EqualTo" Type="Numeric" Size="10" RealTableName="ARCHIVO_SONIDO_DLI" BeginGroup="" EndGroup="" LogicalOperator="And" Order="0" /><Condition Name="ARCHIVO_SONIDO_DLI.ID_CONSECUTIVO" Expression="[Consecutivo]" Operator="EqualTo" Type="Numeric" Size="10" RealTableName="ARCHIVO_SONIDO_DLI" BeginGroup="" EndGroup="" LogicalOperator="None" Order="1" /></Filters></root><roles>All</roles><HaveChildrenWithHistory>false</HaveChildrenWithHistory><Parameters><QueryParameters Name="Secuencia" CustomName="" Type="Numeric" Behavior="" Length="10" Default="" Required="true" EnableControl="" EnableValue="" BeginRangeControl="" SkipColumns="0" SkipRows="0" Enabled="true"><Captions><Caption Language="1" Value="Secuencia" /><Caption Language="2" Value="Secuencia" /></Captions><ToolTips><ToolTip Language="1" Value="Secuencia" /><ToolTip Language="2" Value="Secuencia" /></ToolTips><Legends><Legend Language="1" /><Legend Language="2" /></Legends></QueryParameters><QueryParameters Name="Consecutivo" CustomName="" Type="Numeric" Behavior="" Length="10" Default="" Required="true" EnableControl="" EnableValue="" BeginRangeControl="" SkipColumns="0" SkipRows="0" Enabled="true"><Captions><Caption Language="1" Value="Consecutivo" /><Caption Language="2" Value="Consecutivo" /></Captions><ToolTips><ToolTip Language="1" Value="Consecutivo" /><ToolTip Language="2" Value="Consecutivo" /></ToolTips><Legends><Legend Language="1" /><Legend Language="2" /></Legends></QueryParameters></Parameters></metadata>