<Specification>
<Widget ModelId='2e8caea5-e56f-46ea-ad00-cb9717932fa0' Name='HT5OnLineServiceUnderwriterII' Description='HT5 Auto Servicio2' DefaultState='&lt;state&gt;&lt;/state&gt;' 
        VersionNo='1' IsDefault='0' OrderNo='1' IsAnonymouAllow='0' Url='/fasi/dli/forms/HT5OnLineServiceUnderwriterIIWidget.html' Icon='~\images\Dropthings\Form.png'>
   <Roles>
      <Role Id='Suscriptor' Name='Suscriptor'/>
   </Roles>
</Widget>
<Category Id='36' Name='HT5'/>
<Owner Id='46' Name='HT5'/>
<Deploy When='04/04/2019 13:21:22' User='Nelson' Computer='POSEIDON' Server='https://40.114.32.131' DesignerVersion='7.1.2' Release='2' ModelName='HT5OnLineServiceUnderwriterII' ModelKind='Form' Draft='False' />
   <Resources>
      <Resource LanguageId='1' Title='On Line Service' Description='HT5 Auto Servicio2'/>
      <Resource LanguageId='2' Title='Auto servicio para suscriptores' Description='HT5 Auto Servicio2'/>
   </Resources>
</Specification>
